Workbook

Sheet 使用说明
A1: 📊 个人财务管理模板 v1.0
A4: 📋 功能概览 | B4: 全自动记账、分类统计、月度汇总、可视化图表
A6: 📌 使用步骤
A7: 步骤 1 | B7: 在【记账记录】表中逐笔录入收支明细
A8: 步骤 2 | B8: 在【类别管理】中可自定义收支类别
A9: 步骤 3 | B9: 设定月度预算，自动监控超支情况
A10: 步骤 4 | B10: 切换到【仪表盘】查看自动生成的图表分析
A11: 步骤 5 | B11: 查看【月度汇总】了解每月收支概况
A13: 💡 小贴士
A14: • | B14: 日期格式请填写 YYYY-MM-DD（如 2026-05-21）
A15: • | B15: 收入金额填正数，支出金额填正数（系统自动区分）
A16: • | B16: 建议每周录入一次，保持数据及时
A17: • | B17: 所有图表和汇总数据会自动更新，无需手动操作
A19: 🎨 颜色说明
A20: 🟢 绿色 | B20: 代表收入 / 正数
A21: 🔴 红色 | B21: 代表支出 / 负数
A22: 🔵 蓝色 | B22: 代表汇总统计数据
A24: ⚠️ 注意事项
A25: • | B25: 请勿删除或重命名工作表，否则公式会出错
A26: • | B26: 建议定期备份文件
A27: • | B27: 本模板为通用版本，可根据个人需求调整

Sheet 类别管理
A1: 📂 收支类别管理
A2: 序号 | B2: 类别名称 | C2: 类型 | D2: 说明
A3: 1 | B3: 工资薪金 | C3: 收入 | D3: 工资、奖金、津贴
A4: 2 | B4: 投资收益 | C4: 收入 | D4: 股票、基金、理财收益
A5: 3 | B5: 兼职收入 | C5: 收入 | D5: 自由职业、副业
A6: 4 | B6: 礼金红包 | C6: 收入 | D6: 收到红包、礼金
A7: 5 | B7: 其他收入 | C7: 收入 | D7: 其他杂项收入
A8: 6 | B8: 餐饮饮食 | C8: 支出 | D8: 三餐、外卖、零食饮料
A9: 7 | B9: 交通出行 | C9: 支出 | D9: 地铁公交、打车、油费
A10: 8 | B10: 住房物业 | C10: 支出 | D10: 房租/房贷、水电燃气、物业
A11: 9 | B11: 购物消费 | C11: 支出 | D11: 日用品、服装、数码产品
A12: 10 | B12: 娱乐休闲 | C12: 支出 | D12: 电影、游戏、运动健身
A13: 11 | B13: 通讯网络 | C13: 支出 | D13: 话费、网费
A14: 12 | B14: 医疗健康 | C14: 支出 | D14: 看病买药、体检、保险
... A17: 15 | B17: 其他支出 | C17: 支出 | D17: 其他杂项支出

Sheet 记账记录
A1: 📝 收支记账记录
A2: 当月收入： | C2: =SUMPRODUCT(($D$4:$D$42="收入")*($E$4:$E$42)) | D2: 当月支出： | F2: =SUMPRODUCT(($D$4:$D$42="支出")*($E$4:$E$42)) | G2: =C2-F2
A3: 序号 | B3: 日期 | C3: 类别 | D3: 类型 | E3: 金额(元) | F3: 支付方式 | G3: 备注
A4: 1 | B4: 2026-05-01 | C4: 工资薪金 | D4: 收入 | E4: 15000 | F4: 银行转账 | G4: 5月份工资
A5: 2 | B5: 2026-05-03 | C5: 餐饮饮食 | D5: 支出 | E5: 35 | F5: 微信支付 | G5: 午餐
A6: 3 | B6: 2026-05-04 | C6: 交通出行 | D6: 支出 | E6: 6 | F6: 支付宝 | G6: 地铁
A7: 4 | B7: 2026-05-05 | C7: 购物消费 | D7: 支出 | E7: 299 | F7: 信用卡 | G7: 买了一件T恤
A8: 5 | B8: 2026-05-06 | C8: 餐饮饮食 | D8: 支出 | E8: 68 | F8: 微信支付 | G8: 和朋友晚餐
A9: 6 | B9: 2026-05-07 | C9: 交通出行 | D9: 支出 | E9: 12 | F9: 支付宝 | G9: 打车回家
A10: 7 | B10: 2026-05-08 | C10: 住房物业 | D10: 支出 | E10: 3500 | F10: 银行转账 | G10: 房租
A11: 8 | B11: 2026-05-10 | C11: 投资收益 | D11: 收入 | E11: 520 | F11: 银行转账 | G11: 基金分红
A12: 9 | B12: 2026-05-11 | C12: 餐饮饮食 | D12: 支出 | E12: 25 | F12: 微信支付 | G12: 早餐+咖啡
A13: 10 | B13: 2026-05-12 | C13: 娱乐休闲 | D13: 支出 | E13: 45 | F13: 支付宝 | G13: 电影票
A14: 11 | B14: 2026-05-13 | C14: 通讯网络 | D14: 支出 | E14: 100 | F14: 支付宝 | G14: 话费充值
A15: 12 | B15: 2026-05-14 | C15: 餐饮饮食 | D15: 支出 | E15: 42 | F15: 微信支付 | G15: 午餐外卖
... A23: 20 | B23: 2026-05-21 | C23: 购物消费 | D23: 支出 | E23: 450 | F23: 信用卡 | G23: 网购

Sheet 仪表盘
A1: 📊 财务仪表盘
A3: 本月总收入 | C3: 本月总支出 | E3: 本月结余 | G3: 预算使用率
A4: =SUMPRODUCT((记账记录!$D$4:$D$1000="收入")*(记账记录!$E$4:$E$1000)) | C4: =SUMPRODUCT((记账记录!$D$4:$D$1000="支出")*(记账记录!$E$4:$E$1000)) | E4: =A4-C4 | G4: =C4/5000
A6: 支出分类汇总 | D6: 收入分类汇总 | G6: 月度趋势
A7: 类别 | B7: 金额 | D7: 类别 | E7: 金额 | G7: 月份 | H7: 收入 | I7: 支出
A8: 餐饮饮食 | B8: =SUMIF(记账记录!C:C,A8,记账记录!E:E) | D8: 工资薪金 | E8: =SUMIF(记账记录!C:C,D8,记账记录!E:E) | G8: 1月
A9: 交通出行 | B9: =SUMIF(记账记录!C:C,A9,记账记录!E:E) | D9: 投资收益 | E9: =SUMIF(记账记录!C:C,D9,记账记录!E:E) | G9: 2月
A10: 住房物业 | B10: =SUMIF(记账记录!C:C,A10,记账记录!E:E) | D10: 兼职收入 | E10: =SUMIF(记账记录!C:C,D10,记账记录!E:E) | G10: 3月
A11: 购物消费 | B11: =SUMIF(记账记录!C:C,A11,记账记录!E:E) | D11: 礼金红包 | E11: =SUMIF(记账记录!C:C,D11,记账记录!E:E) | G11: 4月
A12: 娱乐休闲 | B12: =SUMIF(记账记录!C:C,A12,记账记录!E:E) | D12: 其他收入 | E12: =SUMIF(记账记录!C:C,D12,记账记录!E:E) | G12: 5月
A13: 通讯网络 | B13: =SUMIF(记账记录!C:C,A13,记账记录!E:E) | G13: 6月
A14: 医疗健康 | B14: =SUMIF(记账记录!C:C,A14,记账记录!E:E) | G14: 7月
A15: 学习提升 | B15: =SUMIF(记账记录!C:C,A15,记账记录!E:E) | G15: 8月
A16: 人情往来 | B16: =SUMIF(记账记录!C:C,A16,记账记录!E:E) | G16: 9月
A17: 其他支出 | B17: =SUMIF(记账记录!C:C,A17,记账记录!E:E) | G17: 10月
G18: 11月
G19: 12月

Sheet 月度汇总
A1: 📈 月度收支汇总
A2: 月份 | B2: 收入总额 | C2: 支出总额 | D2: 结余 | E2: 预算 | F2: 预算使用率 | G2: 备注
A3: 1月 | E3: 0
A4: 2月 | E4: 0
A5: 3月 | E5: 0
A6: 4月 | E6: 0
A7: 5月 | E7: 5000
A8: 6月 | E8: 5000
A9: 7月 | E9: 5000
A10: 8月 | E10: 5000
A11: 9月 | E11: 5000
A12: 10月 | E12: 5000
A13: 11月 | E13: 5000
A14: 12月 | E14: 5000
A15: 合计 | B15: =SUM(B3:B14) | C15: =SUM(C3:C14) | D15: =SUM(D3:D14) | E15: =SUM(E3:E14) | F15: =SUM(F3:F14)

Sheet 预算设置
A1: 🎯 月度预算设置
A2: 序号 | B2: 类别 | C2: 月度预算(元) | D2: 已使用(元) | E2: 剩余(元) | F2: 状态
A3: 1 | B3: 餐饮饮食 | D3: =SUMIF(记账记录!C:C,B3,记账记录!E:E) | E3: =IF(C3>0,C3-D3,"") | F3: =IF(C3>0,IF(D3>C3,"⚠️ 超支","✅ 正常"),"")
A4: 2 | B4: 交通出行 | D4: =SUMIF(记账记录!C:C,B4,记账记录!E:E) | E4: =IF(C4>0,C4-D4,"") | F4: =IF(C4>0,IF(D4>C4,"⚠️ 超支","✅ 正常"),"")
A5: 3 | B5: 住房物业 | D5: =SUMIF(记账记录!C:C,B5,记账记录!E:E) | E5: =IF(C5>0,C5-D5,"") | F5: =IF(C5>0,IF(D5>C5,"⚠️ 超支","✅ 正常"),"")
A6: 4 | B6: 购物消费 | D6: =SUMIF(记账记录!C:C,B6,记账记录!E:E) | E6: =IF(C6>0,C6-D6,"") | F6: =IF(C6>0,IF(D6>C6,"⚠️ 超支","✅ 正常"),"")
A7: 5 | B7: 娱乐休闲 | D7: =SUMIF(记账记录!C:C,B7,记账记录!E:E) | E7: =IF(C7>0,C7-D7,"") | F7: =IF(C7>0,IF(D7>C7,"⚠️ 超支","✅ 正常"),"")
A8: 6 | B8: 通讯网络 | D8: =SUMIF(记账记录!C:C,B8,记账记录!E:E) | E8: =IF(C8>0,C8-D8,"") | F8: =IF(C8>0,IF(D8>C8,"⚠️ 超支","✅ 正常"),"")
A9: 7 | B9: 医疗健康 | D9: =SUMIF(记账记录!C:C,B9,记账记录!E:E) | E9: =IF(C9>0,C9-D9,"") | F9: =IF(C9>0,IF(D9>C9,"⚠️ 超支","✅ 正常"),"")
A10: 8 | B10: 学习提升 | D10: =SUMIF(记账记录!C:C,B10,记账记录!E:E) | E10: =IF(C10>0,C10-D10,"") | F10: =IF(C10>0,IF(D10>C10,"⚠️ 超支","✅ 正常"),"")
A11: 9 | B11: 人情往来 | D11: =SUMIF(记账记录!C:C,B11,记账记录!E:E) | E11: =IF(C11>0,C11-D11,"") | F11: =IF(C11>0,IF(D11>C11,"⚠️ 超支","✅ 正常"),"")
A12: 10 | B12: 其他支出 | D12: =SUMIF(记账记录!C:C,B12,记账记录!E:E) | E12: =IF(C12>0,C12-D12,"") | F12: =IF(C12>0,IF(D12>C12,"⚠️ 超支","✅ 正常"),"")
